NameComparator/NameComparator.py
NameComparator/_version.py
NameComparator/requirements.txt
NameComparator/data/frequency/firstNamesUsaTo1950.py
NameComparator/data/frequency/surnamesUsaTo1950.py
NameComparator/data/nicknames/idToNicknameSet.py
NameComparator/data/nicknames/nicknameToId.py
NameComparator/data/pronunciation/ipaAllNames.py
NameComparator/data/pronunciation/ipaCommonWordParts.py
NameComparator/data/rules/rulesIpa.py
NameComparator/data/rules/rulesSpelling.py
NameComparator/src/clean.py
NameComparator/src/comparisons.py
NameComparator/src/insights.py
NameComparator/src/ipa.py
NameComparator/src/modify.py
NameComparator/src/nicknames.py
NameComparator/src/uniqueness.py
NameComparator/src/usefulTools.py
namecomparator-1.0.20.dist-info/LICENSE
namecomparator-1.0.20.dist-info/METADATA
namecomparator-1.0.20.dist-info/WHEEL
namecomparator-1.0.20.dist-info/top_level.txt
namecomparator-1.0.20.dist-info/RECORD
