Metadata-Version: 2.2
Name: NameComparator
Version: 1.0.20
Summary: This is a library used to make fuzzy name comparisons across census records.
Home-page: https://github.com/byuawsfhtl/NameComparator.git
Author: Record Linking Lab
Author-email: recordlinkinglab@gmail.com
Project-URL: Bug Tracker, https://github.com/byuawsfhtl/NameComparator/issues
License-File: LICENSE
Requires-Dist: fuzzywuzzy~=0.18.0
Requires-Dist: python-Levenshtein~=0.25.1
Requires-Dist: Unidecode~=1.3.8
Requires-Dist: numpy~=1.26.4
Requires-Dist: scipy~=1.13.1
Dynamic: author
Dynamic: author-email
Dynamic: description
Dynamic: description-content-type
Dynamic: home-page
Dynamic: project-url
Dynamic: requires-dist
Dynamic: summary
